nameCreator/__init__.py
nameCreator/F/__init__.py
nameCreator/F/firstF.py
nameCreator/F/names/american.txt
nameCreator/F/names/chinese.txt
nameCreator/F/names/chineseR.txt
nameCreator/F/names/finnish.txt
nameCreator/F/names/french.txt
nameCreator/F/names/german.txt
nameCreator/F/names/italian.txt
nameCreator/F/names/japanese.txt
nameCreator/F/names/japaneseR.txt
nameCreator/F/names/russian.txt
nameCreator/F/names/spanish.txt
nameCreator/F/names/swedish.txt
nameCreator/L/__init__.py
nameCreator/L/last.py
nameCreator/L/names/american.txt
nameCreator/L/names/chinese.txt
nameCreator/L/names/chineseR.txt
nameCreator/L/names/finnish.txt
nameCreator/L/names/french.txt
nameCreator/L/names/german.txt
nameCreator/L/names/italian.txt
nameCreator/L/names/japanese.txt
nameCreator/L/names/japaneseR.txt
nameCreator/L/names/russian.txt
nameCreator/L/names/spanish.txt
nameCreator/L/names/swedish.txt
nameCreator/M/__init__.py
nameCreator/M/firstM.py
nameCreator/M/names/american.txt
nameCreator/M/names/chinese.txt
nameCreator/M/names/chineseR.txt
nameCreator/M/names/finnish.txt
nameCreator/M/names/french.txt
nameCreator/M/names/german.txt
nameCreator/M/names/italian.txt
nameCreator/M/names/japanese.txt
nameCreator/M/names/japaneseR.txt
nameCreator/M/names/russian.txt
nameCreator/M/names/spanish.txt
nameCreator/M/names/swedish.txt
nameCreator-1.0.0.data/scripts/nameCreatorCLI.py
nameCreator-1.0.0.dist-info/LICENSE
nameCreator-1.0.0.dist-info/METADATA
nameCreator-1.0.0.dist-info/WHEEL
nameCreator-1.0.0.dist-info/top_level.txt
nameCreator-1.0.0.dist-info/RECORD
