Metadata-Version: 2.1
Name: nameCreator
Version: 1.0.0
Summary: A package to generate names by country
Home-page: https://github.com/JHudd435/nameCreator
Author: Justin Huddleston
Classifier: Programming Language :: Python :: 3
Classifier: License :: OSI Approved :: Apache Software License
Classifier: Operating System :: Microsoft :: Windows
Requires-Python: >=3.6
License-File: LICENSE
Requires-Dist: click
